conftestpy/__init__.py
conftestpy/conftestpy.py
conftestpy-4.35.dist-info/LICENSE
conftestpy-4.35.dist-info/METADATA
conftestpy-4.35.dist-info/WHEEL
conftestpy-4.35.dist-info/top_level.txt
conftestpy-4.35.dist-info/RECORD
