Metadata-Version: 2.1
Name: conftestpy
Version: 4.35
Summary: the best conftestpy.py for pytest
Home-page: https://gitee.com/teark/seliky.git
Author: teark
Author-email: 913355434@qq.com
Classifier: Programming Language :: Python :: 3
Classifier: License :: OSI Approved :: MIT License
Classifier: Operating System :: OS Independent
Requires-Python: >=3.6
License-File: LICENSE
Requires-Dist: pytest-html ==3.1.1
Requires-Dist: pyecharts
Requires-Dist: pillow
Requires-Dist: py
Requires-Dist: lxml
